{"name":"Signup with valid username and valid password","id":"signup;signup-with-valid-username-and-valid-password","scenarioId":"signup:Signup with valid username and valid password","methodName":"Signup with valid username and valid password","testSteps":[{"number":1,"description":"Given I am on the home page","duration":4784,"startTime":"2025-11-12T23:04:14.778776100Z[Europe/London]","screenshots":[{"screenshot":"56f73048c5a0660dcdd282c4d17dbca26c4af362286c50db590a8ef5ed89f85d.png","timeStamp":1762988659562,"screenshotName":"56f73048c5a0660dcdd282c4d17dbca26c4af362286c50db590a8ef5ed89f85d.png"}],"result":"SUCCESS","precondition":false,"level":0},{"number":2,"description":"And I have clicked on the signup button","duration":1576,"startTime":"2025-11-12T23:04:19.573663600Z[Europe/London]","screenshots":[{"screenshot":"c4ebefb8b730b35cdc592aee0a185f1387936d6e3c138d516b0ae7cfe828b9ae.png","timeStamp":1762988661150,"screenshotName":"c4ebefb8b730b35cdc592aee0a185f1387936d6e3c138d516b0ae7cfe828b9ae.png"}],"result":"SUCCESS","precondition":false,"level":0},{"number":3,"description":"When I enter a new username \"Krish\"","duration":287,"startTime":"2025-11-12T23:04:21.154546100Z[Europe/London]","screenshots":[{"screenshot":"99c7d52c998ea38408f8f221cc47721f28a90aaa07a08281d94dd49d9fb6f7d1.png","timeStamp":1762988661442,"screenshotName":"99c7d52c998ea38408f8f221cc47721f28a90aaa07a08281d94dd49d9fb6f7d1.png"}],"result":"SUCCESS","precondition":false,"level":0},{"number":4,"description":"And I enter a password \"Kumari\"","duration":244,"startTime":"2025-11-12T23:04:21.446182100Z[Europe/London]","screenshots":[{"screenshot":"ec6bd838b266b12c0825a36c3583a3981996d9b5e8e9b4632e28e95f154aa2a6.png","timeStamp":1762988661690,"screenshotName":"ec6bd838b266b12c0825a36c3583a3981996d9b5e8e9b4632e28e95f154aa2a6.png"}],"result":"SUCCESS","precondition":false,"level":0},{"number":5,"description":"And I click the signup confirmation button","duration":743,"startTime":"2025-11-12T23:04:21.694901300Z[Europe/London]","result":"SUCCESS","precondition":false,"level":0},{"number":6,"description":"Then I should see a popup message saying \"This user already exist.\"","duration":161,"startTime":"2025-11-12T23:04:22.442658600Z[Europe/London]","screenshots":[{"screenshot":"d3f059d018af50a550517fe361700ce8d72a41bc11218d5d48f247f7680470ed.png","timeStamp":1762988662603,"screenshotName":"d3f059d018af50a550517fe361700ce8d72a41bc11218d5d48f247f7680470ed.png"}],"result":"SUCCESS","precondition":false,"level":0}],"userStory":{"id":"signup","storyName":"Signup","displayName":"Signup","path":"signup","pathElements":[{"name":"signup","description":""}],"narrative":"  In order to be able to make purchases on the website\n  As a new user\n  I want to be able to create an account successfully","type":"feature"},"title":"Signup with valid username and valid password","description":"","tags":[{"name":"Chrome","type":"context","displayName":"Chrome"},{"name":"Windows","type":"context","displayName":"Windows"},{"name":"Chrome, Windows","type":"context","displayName":"Chrome, Windows"},{"name":"Happy","type":"tag","displayName":"Happy"}],"startTime":"2025-11-12T23:04:14.737650300Z[Europe/London]","duration":7871,"projectKey":"","sessionId":"c877b5f9a6214b1e1ca406807a0739a6","driver":"chrome","isManualTestingUpToDate":false,"context":"chrome,windows","manual":false,"testSource":"Cucumber","order":0,"result":"SUCCESS"}